phae/__init__.py
phae/discord/__init__.py
phae-0.0.3.dist-info/LICENSE
phae-0.0.3.dist-info/WHEEL
phae-0.0.3.dist-info/METADATA
phae-0.0.3.dist-info/RECORD
